pulumi_kubernetes_ingress_nginx/__init__.py
pulumi_kubernetes_ingress_nginx/_inputs.py
pulumi_kubernetes_ingress_nginx/_utilities.py
pulumi_kubernetes_ingress_nginx/ingress_controller.py
pulumi_kubernetes_ingress_nginx/outputs.py
pulumi_kubernetes_ingress_nginx/provider.py
pulumi_kubernetes_ingress_nginx/pulumi-plugin.json
pulumi_kubernetes_ingress_nginx/py.typed
pulumi_kubernetes_ingress_nginx-0.1.3.dist-info/METADATA
pulumi_kubernetes_ingress_nginx-0.1.3.dist-info/WHEEL
pulumi_kubernetes_ingress_nginx-0.1.3.dist-info/top_level.txt
pulumi_kubernetes_ingress_nginx-0.1.3.dist-info/RECORD
